appelpy/__init__.py
appelpy/diagnostics.py
appelpy/discrete_model.py
appelpy/eda.py
appelpy/linear_model.py
appelpy/utils.py
appelpy-0.4.2.dist-info/LICENSE.txt
appelpy-0.4.2.dist-info/METADATA
appelpy-0.4.2.dist-info/WHEEL
appelpy-0.4.2.dist-info/top_level.txt
appelpy-0.4.2.dist-info/RECORD
