Metadata-Version: 2.1
Name: appelpy
Version: 0.4.2
Summary: Applied Econometrics Library for Python
Home-page: https://github.com/mfarragher/appelpy
Author: Mark Farragher
License: BSD
Project-URL: Documentation, https://appelpy.readthedocs.io/
Project-URL: Source, https://github.com/mfarragher/appelpy
Keywords: econometrics,regression,statistics,economics,models
Platform: UNKNOWN
Classifier: Development Status :: 3 - Alpha
Classifier: Intended Audience :: Education
Classifier: Intended Audience :: Science/Research
Classifier: Topic :: Scientific/Engineering :: Mathematics
Classifier: Topic :: Office/Business :: Financial
Classifier: Programming Language :: Python :: 3.6
Classifier: Programming Language :: Python :: 3.7
Classifier: License :: OSI Approved :: BSD License
Classifier: Operating System :: OS Independent
Requires-Python: >=3.6
Requires-Dist: pandas (>=0.24)
Requires-Dist: jinja2
Requires-Dist: scipy
Requires-Dist: numpy (>=1.16)
Requires-Dist: statsmodels (>=0.9)
Requires-Dist: patsy
Requires-Dist: seaborn (>=0.9)
Requires-Dist: matplotlib (>=3)
